pypbkdf2/__init__.py
py_pbkdf2-1.0.0.dist-info/LICENSE.md
py_pbkdf2-1.0.0.dist-info/METADATA
py_pbkdf2-1.0.0.dist-info/WHEEL
py_pbkdf2-1.0.0.dist-info/top_level.txt
py_pbkdf2-1.0.0.dist-info/RECORD
