Metadata-Version: 2.1
Name: py-pbkdf2
Version: 1.0.0
Summary: PBKDF2 implementation for Python
Home-page: https://github.com/x-compat/py-pbkdf2
Author: wuriyanto
Author-email: wuriyanto48@yahoo.co.id
License: UNKNOWN
Project-URL: Bug Reports, https://github.com/x-compat/py-pbkdf2/issues
Project-URL: Source, https://github.com/x-compat/py-pbkdf2/
Keywords: password hashing,hash,crypto,security
Platform: UNKNOWN
Classifier: Development Status :: 3 - Alpha
Classifier: Intended Audience :: Developers
Classifier: Environment :: Console
Classifier: License :: OSI Approved :: MIT License
Classifier: Programming Language :: Python :: 3
Classifier: Programming Language :: Python :: 3.5
Classifier: Programming Language :: Python :: 3.6
Classifier: Programming Language :: Python :: 3.7
Classifier: Programming Language :: Python :: 3.8
Classifier: Programming Language :: Python :: 3 :: Only
Classifier: Topic :: Software Development
Classifier: Topic :: Utilities
Requires-Python: >=3.5
License-File: LICENSE.md
